skyeye/__init__.py
skyeye/apk_decompiling.py
skyeye/apk_scanner.py
skyeye/cli.py
skyeye/result_wirter.py
skyeye/version_check.py
skyeye/config/__init__.py
skyeye/config/baksmali-2.5.2.jar
skyeye/config/cli_config.py
skyeye/config/config_center.py
skyeye/config/jd-gui-1.6.6.jar
skyeye/config/__pycache__/__init__.cpython-310.pyc
skyeye/config/__pycache__/cli_config.cpython-310.pyc
skyeye/config/__pycache__/config_center.cpython-310.pyc
skyeye/config/dex-tools-2.1/LICENSE.txt
skyeye/config/dex-tools-2.1/NOTICE.txt
skyeye/config/dex-tools-2.1/d2j-apk-sign.bat
skyeye/config/dex-tools-2.1/d2j-apk-sign.sh
skyeye/config/dex-tools-2.1/d2j-asm-verify.bat
skyeye/config/dex-tools-2.1/d2j-asm-verify.sh
skyeye/config/dex-tools-2.1/d2j-baksmali.bat
skyeye/config/dex-tools-2.1/d2j-baksmali.sh
skyeye/config/dex-tools-2.1/d2j-class-version-switch.bat
skyeye/config/dex-tools-2.1/d2j-class-version-switch.sh
skyeye/config/dex-tools-2.1/d2j-decrypt-string.bat
skyeye/config/dex-tools-2.1/d2j-decrypt-string.sh
skyeye/config/dex-tools-2.1/d2j-dex-recompute-checksum.bat
skyeye/config/dex-tools-2.1/d2j-dex-recompute-checksum.sh
skyeye/config/dex-tools-2.1/d2j-dex-weaver.bat
skyeye/config/dex-tools-2.1/d2j-dex-weaver.sh
skyeye/config/dex-tools-2.1/d2j-dex2jar.bat
skyeye/config/dex-tools-2.1/d2j-dex2jar.sh
skyeye/config/dex-tools-2.1/d2j-dex2smali.bat
skyeye/config/dex-tools-2.1/d2j-dex2smali.sh
skyeye/config/dex-tools-2.1/d2j-jar-access.bat
skyeye/config/dex-tools-2.1/d2j-jar-access.sh
skyeye/config/dex-tools-2.1/d2j-jar-weaver.bat
skyeye/config/dex-tools-2.1/d2j-jar-weaver.sh
skyeye/config/dex-tools-2.1/d2j-jar2dex.bat
skyeye/config/dex-tools-2.1/d2j-jar2dex.sh
skyeye/config/dex-tools-2.1/d2j-jar2jasmin.bat
skyeye/config/dex-tools-2.1/d2j-jar2jasmin.sh
skyeye/config/dex-tools-2.1/d2j-jasmin2jar.bat
skyeye/config/dex-tools-2.1/d2j-jasmin2jar.sh
skyeye/config/dex-tools-2.1/d2j-smali.bat
skyeye/config/dex-tools-2.1/d2j-smali.sh
skyeye/config/dex-tools-2.1/d2j-std-apk.bat
skyeye-3.7.0.dist-info/METADATA
skyeye-3.7.0.dist-info/WHEEL
skyeye-3.7.0.dist-info/entry_points.txt
skyeye-3.7.0.dist-info/top_level.txt
skyeye-3.7.0.dist-info/zip-safe
skyeye-3.7.0.dist-info/RECORD
