Metadata-Version: 2.1
Name: skyeye
Version: 3.7.0
Summary: APK扫描工具
Home-page: https://github.com/wangshuwen1107/skyeye
Author: wangshuwen
Author-email: wnwn7375@outlook.com
License: MIT
Keywords: apk scanner
Requires-Dist: requests
Requires-Dist: PyYaml
